{
    "tareas":[{
        "nombre":"Tarea 1",
        "descripcion":"Descripcion de la tarea 1",
        "fecha":"01/01/2020",
        "hora":"10:00",
        "estado":"Pendiente"
    },{
        "nombre":"Tarea 2",
        "descripcion":"Descripcion de la tarea 2",
        "fecha":"01/01/2020",
        "hora":"10:00",
        "estado":"Pendiente"
    },{
        "nombre":"Tarea 3",
        "descripcion":"Descripcion de la tarea 3",
        "fecha":"01/01/2020",
        "hora":"10:00",
        "estado":"Pendiente"
    },{
        "nombre":"Tarea 4",
        "descripcion":"Descripcion de la tarea 4",
        "fecha":"01/01/2020",
        "hora":"10:00",
        "estado":"Pendiente"
    },{
        "nombre":"Tarea 5",
        "descripcion":"Descripcion de la tarea 5",
        "fecha":"01/01/2020",
        "hora":"10:00",
        "estado":"Pendiente"
    },{
        "nombre":"Tarea 6",
        "descripcion":"Descripcion de la tarea 6",
        "fecha":"01/01/2020",
        "hora":"10:00",
        "estado":"Pendiente"
    },{
        "nombre":"Tarea 7",
        "descripcion":"Descripcion de la tarea 7"}]
}